opentelemetry_exporter_cloudwatch_emf/__init__.py
opentelemetry_exporter_cloudwatch_emf/exporter.py
opentelemetry_exporter_cloudwatch_emf/units.py
opentelemetry_exporter_cloudwatch_emf-0.1.3.dist-info/licenses/LICENSE
opentelemetry_exporter_cloudwatch_emf-0.1.3.dist-info/METADATA
opentelemetry_exporter_cloudwatch_emf-0.1.3.dist-info/WHEEL
opentelemetry_exporter_cloudwatch_emf-0.1.3.dist-info/top_level.txt
opentelemetry_exporter_cloudwatch_emf-0.1.3.dist-info/RECORD
