Metadata-Version: 2.4
Name: opentelemetry-exporter-cloudwatch-emf
Version: 0.1.3
Summary: OpenTelemetry metrics exporter for AWS CloudWatch using Embedded Metric Format (EMF)
Author-email: Darren Haas <mail+pypi@darrenhaas.com>
License: Apache-2.0
Project-URL: Homepage, https://github.com/darrenhaas/cw-emf-exporter
Project-URL: Repository, https://github.com/darrenhaas/cw-emf-exporter
Project-URL: Issues, https://github.com/darrenhaas/cw-emf-exporter/issues
Keywords: opentelemetry,cloudwatch,emf,metrics,aws,observability
Classifier: Development Status :: 4 - Beta
Classifier: Intended Audience :: Developers
Classifier: License :: OSI Approved :: Apache Software License
Classifier: Programming Language :: Python :: 3
Classifier: Programming Language :: Python :: 3.9
Classifier: Programming Language :: Python :: 3.10
Classifier: Programming Language :: Python :: 3.11
Classifier: Programming Language :: Python :: 3.12
Classifier: Topic :: System :: Monitoring
Requires-Python: >=3.9
License-File: LICENSE
Requires-Dist: opentelemetry-sdk>=1.20.0
Provides-Extra: dev
Requires-Dist: pytest>=7.0.0; extra == "dev"
Requires-Dist: pytest-cov>=4.0.0; extra == "dev"
Requires-Dist: black>=24.0.0; extra == "dev"
Requires-Dist: isort>=5.13.0; extra == "dev"
Requires-Dist: flake8>=7.0.0; extra == "dev"
Requires-Dist: mypy>=1.8.0; extra == "dev"
Dynamic: license-file
